algomax_common/__init__.py
algomax_common/messages.py
algomax_common/settings.py
algomax_common/terminal.py
algomax_common/abstraction/__init__.py
algomax_common/abstraction/abstract_account.py
algomax_common/abstraction/abstract_trade.py
algomax_common/logger/__init__.py
algomax_common/logger/access_logger.py
algomax_common/logger/error_logger.py
algomax_common/logger/json_log_formatter.py
algomax_common/logger/json_log_handler.py
algomax_common-0.2.dist-info/LICENSE
algomax_common-0.2.dist-info/METADATA
algomax_common-0.2.dist-info/WHEEL
algomax_common-0.2.dist-info/top_level.txt
algomax_common-0.2.dist-info/RECORD
