Metadata-Version: 2.1
Name: algomax-common
Version: 0.2
Summary: a common package for algomax-cli and algomax-engine
Home-page: https://mabnadp.com
Author: hadi.f
Author-email: h.farhadi@mabnadp.com
License: UNKNOWN
Keywords: algomax-common
Platform: UNKNOWN
Classifier: Programming Language :: Python :: 3
Classifier: License :: OSI Approved :: MIT License
Classifier: Operating System :: OS Independent
Requires-Python: >=3.6
Requires-Dist: logquacious (==0.5.0)
